{
  "responseMetaData": {
    "operation": "getInventorybyCity",
    "statusCode": "0000",
    "statusDesc": "Success",
    "version": "1.0.0"
  },
  "responsePayloadData": {
    "data": {
      "GA": [
        {
          "city": "ACWORTH",
          "pctAvailable": "55.49%",
          "state": "GA",
          "status": "Available",
          "totalAvailable": "849"
        },
        {
          "city": "ALBANY",
          "pctAvailable": "94.66%",
          "state": "GA",
          "status": "Available",
          "totalAvailable": "2343"
        },
        {
          "city": "ALPHARETTA",
          "pctAvailable": "70.81%",
          "state": "GA",
          "status": "Available",
          "totalAvailable": "6603"
        },
        {
          "city": "AMERICUS",
          "pctAvailable": "97.24%",
          "state": "GA",
          "status": "Available",
          "totalAvailable": "1797"
        },
        {
          "city": "ATHENS",
          "pctAvailable": "88.26%",
          "state": "GA",
          "status": "Available",
          "totalAvailable": "5688"
        },
        {
          "city": "ATLANTA",
          "pctAvailable": "75.17%",
          "state": "GA",
          "status": "Available",
          "totalAvailable": "34485"
        },
        {
          "city": "AUBURN",
          "pctAvailable": "78.36%",
          "state": "GA",
          "status": "Available",
          "totalAvailable": "978"
        },
        {
          "city": "AUGUSTA",
          "pctAvailable": "82.29%",
          "state": "GA",
          "status": "Available",
          "totalAvailable": "3807"
        },
        {
          "city": "AUSTELL",
          "pctAvailable": "55.36%",
          "state": "GA",
          "status": "Available",
          "totalAvailable": "1068"
        },
        {
          "city": "BAINBRIDGE",
          "pctAvailable": "98.52%",
          "state": "GA",
          "status": "Available",
          "totalAvailable": "600"
        },
        {
          "city": "BARNESVILLE",
          "pctAvailable": "93.11%",
          "state": "GA",
          "status": "Available",
          "totalAvailable": "609"
        },
        {
          "city": "BAXLEY",
          "pctAvailable": "98.37%",
          "state": "GA",
          "status": "Available",
          "totalAvailable": "546"
        },
        {
          "city": "BETHLEHEM",
          "pctAvailable": "79.87%",
          "state": "GA",
          "status": "Available",
          "totalAvailable": "393"
        },
        {
          "city": "BLAIRSVILLE",
          "pctAvailable": "96.70%",
          "state": "GA",
          "status": "Available",
          "totalAvailable": "792"
        },
        {
          "city": "BLAKELY",
          "pctAvailable": "98.37%",
          "state": "GA",
          "status": "Available",
          "totalAvailable": "546"
        },
        {
          "city": "BLUE RIDGE",
          "pctAvailable": "97.72%",
          "state": "GA",
          "status": "Available",
          "totalAvailable": "1290"
        },
        {
          "city": "BOWDON",
          "pctAvailable": "98.50%",
          "state": "GA",
          "status": "Available",
          "totalAvailable": "591"
        },
        {
          "city": "BREMEN",
          "pctAvailable": "96.85%",
          "state": "GA",
          "status": "Available",
          "totalAvailable": "555"
        },
        {
          "city": "BROOKHAVEN",
          "pctAvailable": "75.42%",
          "state": "GA",
          "status": "Available",
          "totalAvailable": "2421"
        },
        {
          "city": "BRUNSWICK",
          "pctAvailable": "92.83%",
          "state": "GA",
          "status": "Available",
          "totalAvailable": "1089"
        },
        {
          "city": "BUFORD",
          "pctAvailable": "67.59%",
          "state": "GA",
          "status": "Available",
          "totalAvailable": "2559"
        },
        {
          "city": "CALHOUN",
          "pctAvailable": "94.37%",
          "state": "GA",
          "status": "Available",
          "totalAvailable": "1812"
        },
        {
          "city": "CANTON",
          "pctAvailable": "74.66%",
          "state": "GA",
          "status": "Available",
          "totalAvailable": "3651"
        },
        {
          "city": "CARROLLTON",
          "pctAvailable": "84.56%",
          "state": "GA",
          "status": "Available",
          "totalAvailable": "1266"
        },
        {
          "city": "CARTERSVILLE",
          "pctAvailable": "88.72%",
          "state": "GA",
          "status": "Available",
          "totalAvailable": "2361"
        },
        {
          "city": "CEDARTOWN",
          "pctAvailable": "94.49%",
          "state": "GA",
          "status": "Available",
          "totalAvailable": "618"
        },
        {
          "city": "CHAMBLEE",
          "pctAvailable": "68.68%",
          "state": "GA",
          "status": "Available",
          "totalAvailable": "1053"
        },
        {
          "city": "CHATSWORTH",
          "pctAvailable": "95.80%",
          "state": "GA",
          "status": "Available",
          "totalAvailable": "753"
        },
        {
          "city": "CLAXTON",
          "pctAvailable": "94.17%",
          "state": "GA",
          "status": "Available",
          "totalAvailable": "582"
        },
        {
          "city": "CLAYTON",
          "pctAvailable": "96.15%",
          "state": "GA",
          "status": "Available",
          "totalAvailable": "675"
        },
        {
          "city": "COCHRAN",
          "pctAvailable": "96.21%",
          "state": "GA",
          "status": "Available",
          "totalAvailable": "534"
        },
        {
          "city": "COLUMBUS",
          "pctAvailable": "89.48%",
          "state": "GA",
          "status": "Available",
          "totalAvailable": "8785"
        },
        {
          "city": "COMMERCE",
          "pctAvailable": "96.05%",
          "state": "GA",
          "status": "Available",
          "totalAvailable": "585"
        },
        {
          "city": "CONYERS",
          "pctAvailable": "79.98%",
          "state": "GA",
          "status": "Available",
          "totalAvailable": "2841"
        },
        {
          "city": "CORDELE",
          "pctAvailable": "98.16%",
          "state": "GA",
          "status": "Available",
          "totalAvailable": "642"
        },
        {
          "city": "CORNELIA",
          "pctAvailable": "96.70%",
          "state": "GA",
          "status": "Available",
          "totalAvailable": "792"
        },
        {
          "city": "COVINGTON",
          "pctAvailable": "75.55%",
          "state": "GA",
          "status": "Available",
          "totalAvailable": "3375"
        },
        {
          "city": "CUMMING",
          "pctAvailable": "69.72%",
          "state": "GA",
          "status": "Available",
          "totalAvailable": "5196"
        },
        {
          "city": "CUTHBERT",
          "pctAvailable": "96.64%",
          "state": "GA",
          "status": "Available",
          "totalAvailable": "519"
        },
        {
          "city": "DACULA",
          "pctAvailable": "71.56%",
          "state": "GA",
          "status": "Available",
          "totalAvailable": "1832"
        },
        {
          "city": "DALLAS",
          "pctAvailable": "79.90%",
          "state": "GA",
          "status": "Available",
          "totalAvailable": "3006"
        },
        {
          "city": "DALTON",
          "pctAvailable": "91.33%",
          "state": "GA",
          "status": "Available",
          "totalAvailable": "1803"
        },
        {
          "city": "DAWSONVILLE",
          "pctAvailable": "71.47%",
          "state": "GA",
          "status": "Available",
          "totalAvailable": "744"
        },
        {
          "city": "DECATUR",
          "pctAvailable": "72.91%",
          "state": "GA",
          "status": "Available",
          "totalAvailable": "6873"
        },
        {
          "city": "DOUGLAS",
          "pctAvailable": "97.31%",
          "state": "GA",
          "status": "Available",
          "totalAvailable": "1413"
        },
        {
          "city": "DOUGLASVILLE",
          "pctAvailable": "63.00%",
          "state": "GA",
          "status": "Available",
          "totalAvailable": "1635"
        },
        {
          "city": "DUBLIN",
          "pctAvailable": "95.13%",
          "state": "GA",
          "status": "Available",
          "totalAvailable": "528"
        },
        {
          "city": "DULUTH",
          "pctAvailable": "68.54%",
          "state": "GA",
          "status": "Available",
          "totalAvailable": "1608"
        },
        {
          "city": "DUNWOODY",
          "pctAvailable": "79.75%",
          "state": "GA",
          "status": "Available",
          "totalAvailable": "579"
        },
        {
          "city": "EAST ELLIJAY",
          "pctAvailable": "97.82%",
          "state": "GA",
          "status": "Available",
          "totalAvailable": "1350"
        },
        {
          "city": "EAST POINT",
          "pctAvailable": "69.40%",
          "state": "GA",
          "status": "Available",
          "totalAvailable": "1674"
        },
        {
          "city": "EASTMAN",
          "pctAvailable": "97.83%",
          "state": "GA",
          "status": "Available",
          "totalAvailable": "543"
        },
        {
          "city": "EATONTON",
          "pctAvailable": "96.80%",
          "state": "GA",
          "status": "Available",
          "totalAvailable": "546"
        },
        {
          "city": "ELBERTON",
          "pctAvailable": "98.11%",
          "state": "GA",
          "status": "Available",
          "totalAvailable": "624"
        },
        {
          "city": "ELLENWOOD",
          "pctAvailable": "60.09%",
          "state": "GA",
          "status": "Available",
          "totalAvailable": "366"
        },
        {
          "city": "EVANS",
          "pctAvailable": "85.46%",
          "state": "GA",
          "status": "Available",
          "totalAvailable": "3022"
        },
        {
          "city": "FAIRBURN",
          "pctAvailable": "77.38%",
          "state": "GA",
          "status": "Available",
          "totalAvailable": "924"
        },
        {
          "city": "FAYETTEVILLE",
          "pctAvailable": "65.12%",
          "state": "GA",
          "status": "Available",
          "totalAvailable": "1143"
        },
        {
          "city": "FITZGERALD",
          "pctAvailable": "99.01%",
          "state": "GA",
          "status": "Available",
          "totalAvailable": "603"
        },
        {
          "city": "FLOWERY BRANCH",
          "pctAvailable": "74.37%",
          "state": "GA",
          "status": "Available",
          "totalAvailable": "1611"
        },
        {
          "city": "FOREST PARK",
          "pctAvailable": "75.18%",
          "state": "GA",
          "status": "Available",
          "totalAvailable": "1251"
        },
        {
          "city": "FORSYTH",
          "pctAvailable": "91.88%",
          "state": "GA",
          "status": "Available",
          "totalAvailable": "1257"
        },
        {
          "city": "FORT OGLETHORPE",
          "pctAvailable": "96.34%",
          "state": "GA",
          "status": "Available",
          "totalAvailable": "2925"
        },
        {
          "city": "FORT VALLEY",
          "pctAvailable": "96.05%",
          "state": "GA",
          "status": "Available",
          "totalAvailable": "585"
        },
        {
          "city": "GAINESVILLE",
          "pctAvailable": "88.85%",
          "state": "GA",
          "status": "Available",
          "totalAvailable": "3156"
        },
        {
          "city": "GARDEN CITY",
          "pctAvailable": "85.40%",
          "state": "GA",
          "status": "Available",
          "totalAvailable": "474"
        },
        {
          "city": "GREENSBORO",
          "pctAvailable": "89.47%",
          "state": "GA",
          "status": "Available",
          "totalAvailable": "561"
        },
        {
          "city": "GRIFFIN",
          "pctAvailable": "77.17%",
          "state": "GA",
          "status": "Available",
          "totalAvailable": "1065"
        },
        {
          "city": "GROVETOWN",
          "pctAvailable": "80.73%",
          "state": "GA",
          "status": "Available",
          "totalAvailable": "528"
        },
        {
          "city": "HARTWELL",
          "pctAvailable": "97.86%",
          "state": "GA",
          "status": "Available",
          "totalAvailable": "825"
        },
        {
          "city": "HAZLEHURST",
          "pctAvailable": "99.46%",
          "state": "GA",
          "status": "Available",
          "totalAvailable": "561"
        },
        {
          "city": "HINESVILLE",
          "pctAvailable": "90.25%",
          "state": "GA",
          "status": "Available",
          "totalAvailable": "750"
        },
        {
          "city": "HIRAM",
          "pctAvailable": "65.44%",
          "state": "GA",
          "status": "Available",
          "totalAvailable": "375"
        },
        {
          "city": "HOSCHTON",
          "pctAvailable": "82.52%",
          "state": "GA",
          "status": "Available",
          "totalAvailable": "609"
        },
        {
          "city": "HULL",
          "pctAvailable": "92.20%",
          "state": "GA",
          "status": "Available",
          "totalAvailable": "603"
        },
        {
          "city": "JACKSON",
          "pctAvailable": "90.60%",
          "state": "GA",
          "status": "Available",
          "totalAvailable": "723"
        },
        {
          "city": "JASPER",
          "pctAvailable": "93.90%",
          "state": "GA",
          "status": "Available",
          "totalAvailable": "693"
        },
        {
          "city": "JEFFERSON",
          "pctAvailable": "93.47%",
          "state": "GA",
          "status": "Available",
          "totalAvailable": "1074"
        },
        {
          "city": "JESUP",
          "pctAvailable": "98.93%",
          "state": "GA",
          "status": "Available",
          "totalAvailable": "558"
        },
        {
          "city": "JONESBORO",
          "pctAvailable": "62.72%",
          "state": "GA",
          "status": "Available",
          "totalAvailable": "1176"
        },
        {
          "city": "KENNESAW",
          "pctAvailable": "61.03%",
          "state": "GA",
          "status": "Available",
          "totalAvailable": "1269"
        },
        {
          "city": "KINGSLAND",
          "pctAvailable": "93.39%",
          "state": "GA",
          "status": "Available",
          "totalAvailable": "1782"
        },
        {
          "city": "LA GRANGE",
          "pctAvailable": "94.34%",
          "state": "GA",
          "status": "Available",
          "totalAvailable": "3600"
        },
        {
          "city": "LAFAYETTE",
          "pctAvailable": "95.07%",
          "state": "GA",
          "status": "Available",
          "totalAvailable": "579"
        },
        {
          "city": "LAGRANGE",
          "pctAvailable": "89.50%",
          "state": "GA",
          "status": "Available",
          "totalAvailable": "1203"
        },
        {
          "city": "LAWRENCEVILLE",
          "pctAvailable": "67.40%",
          "state": "GA",
          "status": "Available",
          "totalAvailable": "6105"
        },
        {
          "city": "LEESBURG",
          "pctAvailable": "90.82%",
          "state": "GA",
          "status": "Available",
          "totalAvailable": "1188"
        },
        {
          "city": "LILBURN",
          "pctAvailable": "48.16%",
          "state": "GA",
          "status": "Available",
          "totalAvailable": "867"
        },
        {
          "city": "LITHONIA",
          "pctAvailable": "71.59%",
          "state": "GA",
          "status": "Available",
          "totalAvailable": "945"
        },
        {
          "city": "LOGANVILLE",
          "pctAvailable": "51.37%",
          "state": "GA",
          "status": "Available",
          "totalAvailable": "843"
        },
        {
          "city": "MABLETON",
          "pctAvailable": "66.48%",
          "state": "GA",
          "status": "Available",
          "totalAvailable": "369"
        },
        {
          "city": "MACON",
          "pctAvailable": "89.60%",
          "state": "GA",
          "status": "Available",
          "totalAvailable": "5922"
        },
        {
          "city": "MANCHESTER",
          "pctAvailable": "89.36%",
          "state": "GA",
          "status": "Available",
          "totalAvailable": "504"
        },
        {
          "city": "MARIETTA",
          "pctAvailable": "70.54%",
          "state": "GA",
          "status": "Available",
          "totalAvailable": "12207"
        },
        {
          "city": "MARTINEZ",
          "pctAvailable": "85.36%",
          "state": "GA",
          "status": "Available",
          "totalAvailable": "1032"
        },
        {
          "city": "MCDONOUGH",
          "pctAvailable": "48.23%",
          "state": "GA",
          "status": "Available",
          "totalAvailable": "1767"
        },
        {
          "city": "MILLEDGEVILLE",
          "pctAvailable": "90.57%",
          "state": "GA",
          "status": "Available",
          "totalAvailable": "1095"
        },
        {
          "city": "MILTON",
          "pctAvailable": "70.69%",
          "state": "GA",
          "status": "Available",
          "totalAvailable": "1650"
        },
        {
          "city": "MONROE",
          "pctAvailable": "86.52%",
          "state": "GA",
          "status": "Available",
          "totalAvailable": "1194"
        },
        {
          "city": "MONTEZUMA",
          "pctAvailable": "100.00%",
          "state": "GA",
          "status": "Available",
          "totalAvailable": "555"
        },
        {
          "city": "MONTICELLO",
          "pctAvailable": "94.68%",
          "state": "GA",
          "status": "Available",
          "totalAvailable": "534"
        },
        {
          "city": "MORROW",
          "pctAvailable": "68.99%",
          "state": "GA",
          "status": "Available",
          "totalAvailable": "861"
        },
        {
          "city": "MOULTRIE",
          "pctAvailable": "98.22%",
          "state": "GA",
          "status": "Available",
          "totalAvailable": "828"
        },
        {
          "city": "NEWNAN",
          "pctAvailable": "80.72%",
          "state": "GA",
          "status": "Available",
          "totalAvailable": "3141"
        },
        {
          "city": "NORCROSS",
          "pctAvailable": "71.40%",
          "state": "GA",
          "status": "Available",
          "totalAvailable": "3483"
        },
        {
          "city": "OAKWOOD",
          "pctAvailable": "81.30%",
          "state": "GA",
          "status": "Available",
          "totalAvailable": "600"
        },
        {
          "city": "PEACHTREE CITY",
          "pctAvailable": "68.15%",
          "state": "GA",
          "status": "Available",
          "totalAvailable": "1554"
        },
        {
          "city": "PERRY",
          "pctAvailable": "93.96%",
          "state": "GA",
          "status": "Available",
          "totalAvailable": "1729"
        },
        {
          "city": "POOLER",
          "pctAvailable": "91.96%",
          "state": "GA",
          "status": "Available",
          "totalAvailable": "1098"
        },
        {
          "city": "PORT WENTWORTH",
          "pctAvailable": "87.23%",
          "state": "GA",
          "status": "Available",
          "totalAvailable": "492"
        },
        {
          "city": "POWDER SPRINGS",
          "pctAvailable": "49.42%",
          "state": "GA",
          "status": "Available",
          "totalAvailable": "387"
        },
        {
          "city": "RICHMOND HILL",
          "pctAvailable": "89.83%",
          "state": "GA",
          "status": "Available",
          "totalAvailable": "1113"
        },
        {
          "city": "RINCON",
          "pctAvailable": "82.95%",
          "state": "GA",
          "status": "Available",
          "totalAvailable": "1095"
        },
        {
          "city": "RINGGOLD",
          "pctAvailable": "95.40%",
          "state": "GA",
          "status": "Available",
          "totalAvailable": "1995"
        },
        {
          "city": "RIVERDALE",
          "pctAvailable": "77.22%",
          "state": "GA",
          "status": "Available",
          "totalAvailable": "3387"
        },
        {
          "city": "ROME",
          "pctAvailable": "92.69%",
          "state": "GA",
          "status": "Available",
          "totalAvailable": "4831"
        },
        {
          "city": "ROSWELL",
          "pctAvailable": "63.16%",
          "state": "GA",
          "status": "Available",
          "totalAvailable": "3822"
        },
        {
          "city": "SAINT MARYS",
          "pctAvailable": "95.07%",
          "state": "GA",
          "status": "Available",
          "totalAvailable": "579"
        },
        {
          "city": "SAINT SIMONS ISLAND",
          "pctAvailable": "92.90%",
          "state": "GA",
          "status": "Available",
          "totalAvailable": "2787"
        },
        {
          "city": "SANDERSVILLE",
          "pctAvailable": "98.42%",
          "state": "GA",
          "status": "Available",
          "totalAvailable": "2055"
        },
        {
          "city": "SANDY SPRINGS",
          "pctAvailable": "62.12%",
          "state": "GA",
          "status": "Available",
          "totalAvailable": "2574"
        },
        {
          "city": "SAVANNAH",
          "pctAvailable": "87.28%",
          "state": "GA",
          "status": "Available",
          "totalAvailable": "8961"
        },
        {
          "city": "SMYRNA",
          "pctAvailable": "70.89%",
          "state": "GA",
          "status": "Available",
          "totalAvailable": "3624"
        },
        {
          "city": "SNELLVILLE",
          "pctAvailable": "67.75%",
          "state": "GA",
          "status": "Available",
          "totalAvailable": "2742"
        },
        {
          "city": "STATESBORO",
          "pctAvailable": "86.23%",
          "state": "GA",
          "status": "Available",
          "totalAvailable": "564"
        },
        {
          "city": "STOCKBRIDGE",
          "pctAvailable": "51.14%",
          "state": "GA",
          "status": "Available",
          "totalAvailable": "807"
        },
        {
          "city": "STONE MOUNTAIN",
          "pctAvailable": "60.72%",
          "state": "GA",
          "status": "Available",
          "totalAvailable": "1452"
        },
        {
          "city": "SUMMERVILLE",
          "pctAvailable": "96.78%",
          "state": "GA",
          "status": "Available",
          "totalAvailable": "633"
        },
        {
          "city": "SUWANEE",
          "pctAvailable": "72.17%",
          "state": "GA",
          "status": "Available",
          "totalAvailable": "2646"
        },
        {
          "city": "SYLVESTER",
          "pctAvailable": "96.50%",
          "state": "GA",
          "status": "Available",
          "totalAvailable": "579"
        },
        {
          "city": "TALLAPOOSA",
          "pctAvailable": "92.43%",
          "state": "GA",
          "status": "Available",
          "totalAvailable": "513"
        },
        {
          "city": "THOMASVILLE",
          "pctAvailable": "93.57%",
          "state": "GA",
          "status": "Available",
          "totalAvailable": "612"
        },
        {
          "city": "THOMSON",
          "pctAvailable": "94.49%",
          "state": "GA",
          "status": "Available",
          "totalAvailable": "618"
        },
        {
          "city": "TIFTON",
          "pctAvailable": "96.46%",
          "state": "GA",
          "status": "Available",
          "totalAvailable": "1227"
        },
        {
          "city": "TOCCOA",
          "pctAvailable": "94.83%",
          "state": "GA",
          "status": "Available",
          "totalAvailable": "771"
        },
        {
          "city": "TRENTON",
          "pctAvailable": "97.83%",
          "state": "GA",
          "status": "Available",
          "totalAvailable": "543"
        },
        {
          "city": "TUCKER",
          "pctAvailable": "60.99%",
          "state": "GA",
          "status": "Available",
          "totalAvailable": "1107"
        },
        {
          "city": "TYRONE",
          "pctAvailable": "57.02%",
          "state": "GA",
          "status": "Available",
          "totalAvailable": "414"
        },
        {
          "city": "UNION CITY",
          "pctAvailable": "73.15%",
          "state": "GA",
          "status": "Available",
          "totalAvailable": "834"
        },
        {
          "city": "VALDOSTA",
          "pctAvailable": "94.47%",
          "state": "GA",
          "status": "Available",
          "totalAvailable": "2358"
        },
        {
          "city": "VIDALIA",
          "pctAvailable": "97.29%",
          "state": "GA",
          "status": "Available",
          "totalAvailable": "540"
        },
        {
          "city": "VILLA RICA",
          "pctAvailable": "87.45%",
          "state": "GA",
          "status": "Available",
          "totalAvailable": "2655"
        },
        {
          "city": "WARNER ROBINS",
          "pctAvailable": "88.71%",
          "state": "GA",
          "status": "Available",
          "totalAvailable": "5289"
        },
        {
          "city": "WASHINGTON",
          "pctAvailable": "94.03%",
          "state": "GA",
          "status": "Available",
          "totalAvailable": "615"
        },
        {
          "city": "WATKINSVILLE",
          "pctAvailable": "88.83%",
          "state": "GA",
          "status": "Available",
          "totalAvailable": "1599"
        },
        {
          "city": "WAYCROSS",
          "pctAvailable": "95.87%",
          "state": "GA",
          "status": "Available",
          "totalAvailable": "627"
        },
        {
          "city": "WAYNESBORO",
          "pctAvailable": "96.05%",
          "state": "GA",
          "status": "Available",
          "totalAvailable": "585"
        },
        {
          "city": "WINDER",
          "pctAvailable": "90.07%",
          "state": "GA",
          "status": "Available",
          "totalAvailable": "1116"
        },
        {
          "city": "WOODSTOCK",
          "pctAvailable": "69.52%",
          "state": "GA",
          "status": "Available",
          "totalAvailable": "2409"
        }
      ]
    },
    "isBookingCompleted": false
  }
}
