{
  "responseMetaData": {
    "operation": "getInventorybyCity",
    "statusCode": "0000",
    "statusDesc": "Success",
    "version": "1.0.0"
  },
  "responsePayloadData": {
    "data": {
      "OH": [
        {
          "city": "AKRON",
          "state": "OH",
          "status": "Fully Booked"
        },
        {
          "city": "AMELIA",
          "state": "OH",
          "status": "Fully Booked"
        },
        {
          "city": "AMHERST",
          "state": "OH",
          "status": "Fully Booked"
        },
        {
          "city": "ASHLAND",
          "state": "OH",
          "status": "Fully Booked"
        },
        {
          "city": "ASHTABULA",
          "state": "OH",
          "status": "Fully Booked"
        },
        {
          "city": "ATHENS",
          "state": "OH",
          "status": "Fully Booked"
        },
        {
          "city": "AURORA",
          "state": "OH",
          "status": "Fully Booked"
        },
        {
          "city": "AVON",
          "state": "OH",
          "status": "Fully Booked"
        },
        {
          "city": "AVON LAKE",
          "state": "OH",
          "status": "Fully Booked"
        },
        {
          "city": "BARBERTON",
          "state": "OH",
          "status": "Fully Booked"
        },
        {
          "city": "BAY VILLAGE",
          "state": "OH",
          "status": "Fully Booked"
        },
        {
          "city": "BEAVERCREEK",
          "state": "OH",
          "status": "Fully Booked"
        },
        {
          "city": "BEDFORD",
          "state": "OH",
          "status": "Fully Booked"
        },
        {
          "city": "BELLEFONTAINE",
          "state": "OH",
          "status": "Fully Booked"
        },
        {
          "city": "BELLEVUE",
          "state": "OH",
          "status": "Fully Booked"
        },
        {
          "city": "BELPRE",
          "state": "OH",
          "status": "Fully Booked"
        },
        {
          "city": "BEREA",
          "state": "OH",
          "status": "Fully Booked"
        },
        {
          "city": "BERLIN",
          "state": "OH",
          "status": "Fully Booked"
        },
        {
          "city": "BETHEL",
          "state": "OH",
          "status": "Fully Booked"
        },
        {
          "city": "BLANCHESTER",
          "state": "OH",
          "status": "Fully Booked"
        },
        {
          "city": "BLUE ASH",
          "state": "OH",
          "status": "Fully Booked"
        },
        {
          "city": "BLUFFTON",
          "state": "OH",
          "status": "Fully Booked"
        },
        {
          "city": "BOARDMAN",
          "state": "OH",
          "status": "Fully Booked"
        },
        {
          "city": "BOWLING GREEN",
          "state": "OH",
          "status": "Fully Booked"
        },
        {
          "city": "BRECKSVILLE",
          "state": "OH",
          "status": "Fully Booked"
        },
        {
          "city": "BROOKPARK",
          "state": "OH",
          "status": "Fully Booked"
        },
        {
          "city": "BROOKVILLE",
          "state": "OH",
          "status": "Fully Booked"
        },
        {
          "city": "BRUNSWICK",
          "state": "OH",
          "status": "Fully Booked"
        },
        {
          "city": "BRYAN",
          "state": "OH",
          "status": "Fully Booked"
        },
        {
          "city": "BUCYRUS",
          "state": "OH",
          "status": "Fully Booked"
        },
        {
          "city": "CAMBRIDGE",
          "state": "OH",
          "status": "Fully Booked"
        },
        {
          "city": "CANAL WINCHESTER",
          "state": "OH",
          "status": "Fully Booked"
        },
        {
          "city": "CANFIELD",
          "state": "OH",
          "status": "Fully Booked"
        },
        {
          "city": "CANTON",
          "state": "OH",
          "status": "Fully Booked"
        },
        {
          "city": "CELINA",
          "state": "OH",
          "status": "Fully Booked"
        },
        {
          "city": "CENTERVILLE",
          "state": "OH",
          "status": "Fully Booked"
        },
        {
          "city": "CHAGRIN FALLS",
          "state": "OH",
          "status": "Fully Booked"
        },
        {
          "city": "CHARDON",
          "state": "OH",
          "status": "Fully Booked"
        },
        {
          "city": "CHESAPEAKE",
          "state": "OH",
          "status": "Fully Booked"
        },
        {
          "city": "CHESTERLAND",
          "state": "OH",
          "status": "Fully Booked"
        },
        {
          "city": "CHEVIOT",
          "state": "OH",
          "status": "Fully Booked"
        },
        {
          "city": "CHILLICOTHE",
          "state": "OH",
          "status": "Fully Booked"
        },
        {
          "city": "CINCINNATI",
          "state": "OH",
          "status": "Fully Booked"
        },
        {
          "city": "CIRCLEVILLE",
          "state": "OH",
          "status": "Fully Booked"
        },
        {
          "city": "CLEVELAND",
          "state": "OH",
          "status": "Fully Booked"
        },
        {
          "city": "CLEVELAND HEIGHTS",
          "state": "OH",
          "status": "Fully Booked"
        },
        {
          "city": "COLUMBUS",
          "state": "OH",
          "status": "Fully Booked"
        },
        {
          "city": "CONNEAUT",
          "state": "OH",
          "status": "Fully Booked"
        },
        {
          "city": "COPLEY",
          "state": "OH",
          "status": "Fully Booked"
        },
        {
          "city": "COSHOCTON",
          "state": "OH",
          "status": "Fully Booked"
        },
        {
          "city": "CUYAHOGA FALLS",
          "state": "OH",
          "status": "Fully Booked"
        },
        {
          "city": "DAYTON",
          "state": "OH",
          "status": "Fully Booked"
        },
        {
          "city": "DELAWARE",
          "state": "OH",
          "status": "Fully Booked"
        },
        {
          "city": "DENNISON",
          "state": "OH",
          "status": "Fully Booked"
        },
        {
          "city": "DOVER",
          "state": "OH",
          "status": "Fully Booked"
        },
        {
          "city": "DOYLESTOWN",
          "state": "OH",
          "status": "Fully Booked"
        },
        {
          "city": "DUBLIN",
          "state": "OH",
          "status": "Fully Booked"
        },
        {
          "city": "EATON",
          "state": "OH",
          "status": "Fully Booked"
        },
        {
          "city": "ELYRIA",
          "state": "OH",
          "status": "Fully Booked"
        },
        {
          "city": "EUCLID",
          "state": "OH",
          "status": "Fully Booked"
        },
        {
          "city": "FAIRBORN",
          "state": "OH",
          "status": "Fully Booked"
        },
        {
          "city": "FAIRFIELD",
          "state": "OH",
          "status": "Fully Booked"
        },
        {
          "city": "FAIRLAWN",
          "state": "OH",
          "status": "Fully Booked"
        },
        {
          "city": "FAIRVIEW PARK",
          "state": "OH",
          "status": "Fully Booked"
        },
        {
          "city": "FINDLAY",
          "state": "OH",
          "status": "Fully Booked"
        },
        {
          "city": "FRANKLIN",
          "state": "OH",
          "status": "Fully Booked"
        },
        {
          "city": "FREMONT",
          "state": "OH",
          "status": "Fully Booked"
        },
        {
          "city": "GAHANNA",
          "state": "OH",
          "status": "Fully Booked"
        },
        {
          "city": "GALLIPOLIS",
          "state": "OH",
          "status": "Fully Booked"
        },
        {
          "city": "GALLOWAY",
          "state": "OH",
          "status": "Fully Booked"
        },
        {
          "city": "GARFIELD HEIGHTS",
          "state": "OH",
          "status": "Fully Booked"
        },
        {
          "city": "GENEVA",
          "state": "OH",
          "status": "Fully Booked"
        },
        {
          "city": "GEORGETOWN",
          "state": "OH",
          "status": "Fully Booked"
        },
        {
          "city": "GERMANTOWN",
          "state": "OH",
          "status": "Fully Booked"
        },
        {
          "city": "GIBSONBURG",
          "state": "OH",
          "status": "Fully Booked"
        },
        {
          "city": "GRANVILLE",
          "state": "OH",
          "status": "Fully Booked"
        },
        {
          "city": "GREENVILLE",
          "state": "OH",
          "status": "Fully Booked"
        },
        {
          "city": "GROVE CITY",
          "state": "OH",
          "status": "Fully Booked"
        },
        {
          "city": "HAMILTON",
          "state": "OH",
          "status": "Fully Booked"
        },
        {
          "city": "HARRISON",
          "state": "OH",
          "status": "Fully Booked"
        },
        {
          "city": "HARTVILLE",
          "state": "OH",
          "status": "Fully Booked"
        },
        {
          "city": "HEATH",
          "state": "OH",
          "status": "Fully Booked"
        },
        {
          "city": "HILLIARD",
          "state": "OH",
          "status": "Fully Booked"
        },
        {
          "city": "HILLSBORO",
          "state": "OH",
          "status": "Fully Booked"
        },
        {
          "city": "HINCKLEY",
          "state": "OH",
          "status": "Fully Booked"
        },
        {
          "city": "HUBBARD",
          "state": "OH",
          "status": "Fully Booked"
        },
        {
          "city": "HUBER HEIGHTS",
          "state": "OH",
          "status": "Fully Booked"
        },
        {
          "city": "HUDSON",
          "state": "OH",
          "status": "Fully Booked"
        },
        {
          "city": "INDEPENDENCE",
          "state": "OH",
          "status": "Fully Booked"
        },
        {
          "city": "IRONTON",
          "state": "OH",
          "status": "Fully Booked"
        },
        {
          "city": "JACKSON",
          "state": "OH",
          "status": "Fully Booked"
        },
        {
          "city": "JOHNSTOWN",
          "state": "OH",
          "status": "Fully Booked"
        },
        {
          "city": "KENT",
          "state": "OH",
          "status": "Fully Booked"
        },
        {
          "city": "KENTON",
          "state": "OH",
          "status": "Fully Booked"
        },
        {
          "city": "KETTERING",
          "state": "OH",
          "status": "Fully Booked"
        },
        {
          "city": "LAKEWOOD",
          "state": "OH",
          "status": "Fully Booked"
        },
        {
          "city": "LANCASTER",
          "state": "OH",
          "status": "Fully Booked"
        },
        {
          "city": "LEBANON",
          "state": "OH",
          "status": "Fully Booked"
        },
        {
          "city": "LEWIS CENTER",
          "state": "OH",
          "status": "Fully Booked"
        },
        {
          "city": "LIMA",
          "state": "OH",
          "status": "Fully Booked"
        },
        {
          "city": "LODI",
          "state": "OH",
          "status": "Fully Booked"
        },
        {
          "city": "LOGAN",
          "state": "OH",
          "status": "Fully Booked"
        },
        {
          "city": "LONDON",
          "state": "OH",
          "status": "Fully Booked"
        },
        {
          "city": "LORAIN",
          "state": "OH",
          "status": "Fully Booked"
        },
        {
          "city": "LOVELAND",
          "state": "OH",
          "status": "Fully Booked"
        },
        {
          "city": "LYNDHURST",
          "state": "OH",
          "status": "Fully Booked"
        },
        {
          "city": "MAINEVILLE",
          "state": "OH",
          "status": "Fully Booked"
        },
        {
          "city": "MANSFIELD",
          "state": "OH",
          "status": "Fully Booked"
        },
        {
          "city": "MARIETTA",
          "state": "OH",
          "status": "Fully Booked"
        },
        {
          "city": "MARION",
          "state": "OH",
          "status": "Fully Booked"
        },
        {
          "city": "MARTINS FERRY",
          "state": "OH",
          "status": "Fully Booked"
        },
        {
          "city": "MARYSVILLE",
          "state": "OH",
          "status": "Fully Booked"
        },
        {
          "city": "MASON",
          "state": "OH",
          "status": "Fully Booked"
        },
        {
          "city": "MASSILLON",
          "state": "OH",
          "status": "Fully Booked"
        },
        {
          "city": "MAYFIELD HEIGHTS",
          "state": "OH",
          "status": "Fully Booked"
        },
        {
          "city": "MAYFIELD VLG",
          "state": "OH",
          "status": "Fully Booked"
        },
        {
          "city": "MEDINA",
          "state": "OH",
          "status": "Fully Booked"
        },
        {
          "city": "MENTOR",
          "state": "OH",
          "status": "Fully Booked"
        },
        {
          "city": "MIAMISBURG",
          "state": "OH",
          "status": "Fully Booked"
        },
        {
          "city": "MIDDLEBURG HEIGHTS",
          "state": "OH",
          "status": "Fully Booked"
        },
        {
          "city": "MIDDLEFIELD",
          "state": "OH",
          "status": "Fully Booked"
        },
        {
          "city": "MIDDLETOWN",
          "state": "OH",
          "status": "Fully Booked"
        },
        {
          "city": "MILFORD",
          "state": "OH",
          "status": "Fully Booked"
        },
        {
          "city": "MOGADORE",
          "state": "OH",
          "status": "Fully Booked"
        },
        {
          "city": "MONTGOMERY",
          "state": "OH",
          "status": "Fully Booked"
        },
        {
          "city": "MORAINE",
          "state": "OH",
          "status": "Fully Booked"
        },
        {
          "city": "MOUNT HEALTHY",
          "state": "OH",
          "status": "Fully Booked"
        },
        {
          "city": "MOUNT VERNON",
          "state": "OH",
          "status": "Fully Booked"
        },
        {
          "city": "NEW ALBANY",
          "state": "OH",
          "status": "Fully Booked"
        },
        {
          "city": "NEW BOSTON",
          "state": "OH",
          "status": "Fully Booked"
        },
        {
          "city": "NEW CARLISLE",
          "state": "OH",
          "status": "Fully Booked"
        },
        {
          "city": "NEW LEBANON",
          "state": "OH",
          "status": "Fully Booked"
        },
        {
          "city": "NEW LEXINGTON",
          "state": "OH",
          "status": "Fully Booked"
        },
        {
          "city": "NEWARK",
          "state": "OH",
          "status": "Fully Booked"
        },
        {
          "city": "NILES",
          "state": "OH",
          "status": "Fully Booked"
        },
        {
          "city": "NORTH CANTON",
          "state": "OH",
          "status": "Fully Booked"
        },
        {
          "city": "NORTH OLMSTED",
          "state": "OH",
          "status": "Fully Booked"
        },
        {
          "city": "NORTH RIDGEVILLE",
          "state": "OH",
          "status": "Fully Booked"
        },
        {
          "city": "NORTH ROYALTON",
          "state": "OH",
          "status": "Fully Booked"
        },
        {
          "city": "NORTHFIELD",
          "state": "OH",
          "status": "Fully Booked"
        },
        {
          "city": "NORTHFIELD CENTER",
          "state": "OH",
          "status": "Fully Booked"
        },
        {
          "city": "NORTON",
          "state": "OH",
          "status": "Fully Booked"
        },
        {
          "city": "NORWALK",
          "state": "OH",
          "status": "Fully Booked"
        },
        {
          "city": "NORWOOD",
          "state": "OH",
          "status": "Fully Booked"
        },
        {
          "city": "OAK HILL",
          "state": "OH",
          "status": "Fully Booked"
        },
        {
          "city": "OAKWOOD",
          "state": "OH",
          "status": "Fully Booked"
        },
        {
          "city": "OBERLIN",
          "state": "OH",
          "status": "Fully Booked"
        },
        {
          "city": "OLMSTED TOWNSHIP",
          "state": "OH",
          "status": "Fully Booked"
        },
        {
          "city": "OREGON",
          "state": "OH",
          "status": "Fully Booked"
        },
        {
          "city": "ORRVILLE",
          "state": "OH",
          "status": "Fully Booked"
        },
        {
          "city": "OXFORD",
          "state": "OH",
          "status": "Fully Booked"
        },
        {
          "city": "PAINESVILLE",
          "state": "OH",
          "status": "Fully Booked"
        },
        {
          "city": "PARMA",
          "state": "OH",
          "status": "Fully Booked"
        },
        {
          "city": "PATASKALA",
          "state": "OH",
          "status": "Fully Booked"
        },
        {
          "city": "PICKERINGTON",
          "state": "OH",
          "status": "Fully Booked"
        },
        {
          "city": "PIQUA",
          "state": "OH",
          "status": "Fully Booked"
        },
        {
          "city": "PORTSMOUTH",
          "state": "OH",
          "status": "Fully Booked"
        },
        {
          "city": "POWELL",
          "state": "OH",
          "status": "Fully Booked"
        },
        {
          "city": "RAVENNA",
          "state": "OH",
          "status": "Fully Booked"
        },
        {
          "city": "REYNOLDSBURG",
          "state": "OH",
          "status": "Fully Booked"
        },
        {
          "city": "RICHMOND HEIGHTS",
          "state": "OH",
          "status": "Fully Booked"
        },
        {
          "city": "ROCKY RIVER",
          "state": "OH",
          "status": "Fully Booked"
        },
        {
          "city": "SAINT CLAIRSVILLE",
          "state": "OH",
          "status": "Fully Booked"
        },
        {
          "city": "SANDUSKY",
          "state": "OH",
          "status": "Fully Booked"
        },
        {
          "city": "SHAKER HEIGHTS",
          "state": "OH",
          "status": "Fully Booked"
        },
        {
          "city": "SHARONVILLE",
          "state": "OH",
          "status": "Fully Booked"
        },
        {
          "city": "SHREVE",
          "state": "OH",
          "status": "Fully Booked"
        },
        {
          "city": "SIDNEY",
          "state": "OH",
          "status": "Fully Booked"
        },
        {
          "city": "SOLON",
          "state": "OH",
          "status": "Fully Booked"
        },
        {
          "city": "SOUTH EUCLID",
          "state": "OH",
          "status": "Fully Booked"
        },
        {
          "city": "SOUTH LEBANON",
          "state": "OH",
          "status": "Fully Booked"
        },
        {
          "city": "SPRINGBORO",
          "state": "OH",
          "status": "Fully Booked"
        },
        {
          "city": "SPRINGDALE",
          "state": "OH",
          "status": "Fully Booked"
        },
        {
          "city": "SPRINGFIELD",
          "state": "OH",
          "status": "Fully Booked"
        },
        {
          "city": "STEUBENVILLE",
          "state": "OH",
          "status": "Fully Booked"
        },
        {
          "city": "STOW",
          "state": "OH",
          "status": "Fully Booked"
        },
        {
          "city": "STREETSBORO",
          "state": "OH",
          "status": "Fully Booked"
        },
        {
          "city": "STRONGSVILLE",
          "state": "OH",
          "status": "Fully Booked"
        },
        {
          "city": "STRUTHERS",
          "state": "OH",
          "status": "Fully Booked"
        },
        {
          "city": "SUNBURY",
          "state": "OH",
          "status": "Fully Booked"
        },
        {
          "city": "SYLVANIA",
          "state": "OH",
          "status": "Fully Booked"
        },
        {
          "city": "TIFFIN",
          "state": "OH",
          "status": "Fully Booked"
        },
        {
          "city": "TIPP CITY",
          "state": "OH",
          "status": "Fully Booked"
        },
        {
          "city": "TOLEDO",
          "state": "OH",
          "status": "Fully Booked"
        },
        {
          "city": "TROTWOOD",
          "state": "OH",
          "status": "Fully Booked"
        },
        {
          "city": "TROY",
          "state": "OH",
          "status": "Fully Booked"
        },
        {
          "city": "TWINSBURG",
          "state": "OH",
          "status": "Fully Booked"
        },
        {
          "city": "UNION",
          "state": "OH",
          "status": "Fully Booked"
        },
        {
          "city": "UNIONTOWN",
          "state": "OH",
          "status": "Fully Booked"
        },
        {
          "city": "UNIVERSITY HEIGHTS",
          "state": "OH",
          "status": "Fully Booked"
        },
        {
          "city": "UPPER ARLINGTON",
          "state": "OH",
          "status": "Fully Booked"
        },
        {
          "city": "URBANA",
          "state": "OH",
          "status": "Fully Booked"
        },
        {
          "city": "VAN WERT",
          "state": "OH",
          "status": "Fully Booked"
        },
        {
          "city": "WADSWORTH",
          "state": "OH",
          "status": "Fully Booked"
        },
        {
          "city": "WAPAKONETA",
          "state": "OH",
          "status": "Fully Booked"
        },
        {
          "city": "WARREN",
          "state": "OH",
          "status": "Fully Booked"
        },
        {
          "city": "WARRENSVILLE HEIGHTS",
          "state": "OH",
          "status": "Fully Booked"
        },
        {
          "city": "WASHINGTON COURT HOUSE",
          "state": "OH",
          "status": "Fully Booked"
        },
        {
          "city": "WAVERLY",
          "state": "OH",
          "status": "Fully Booked"
        },
        {
          "city": "WEST CHESTER",
          "state": "OH",
          "status": "Fully Booked"
        },
        {
          "city": "WESTERVILLE",
          "state": "OH",
          "status": "Fully Booked"
        },
        {
          "city": "WESTLAKE",
          "state": "OH",
          "status": "Fully Booked"
        },
        {
          "city": "WHITEHALL",
          "state": "OH",
          "status": "Fully Booked"
        },
        {
          "city": "WILLOUGHBY",
          "state": "OH",
          "status": "Fully Booked"
        },
        {
          "city": "WILLOUGHBY HILLS",
          "state": "OH",
          "status": "Fully Booked"
        },
        {
          "city": "WILMINGTON",
          "state": "OH",
          "status": "Fully Booked"
        },
        {
          "city": "WOODMERE",
          "state": "OH",
          "status": "Fully Booked"
        },
        {
          "city": "WOODVILLE",
          "state": "OH",
          "status": "Fully Booked"
        },
        {
          "city": "WOOSTER",
          "state": "OH",
          "status": "Fully Booked"
        },
        {
          "city": "WORTHINGTON",
          "state": "OH",
          "status": "Fully Booked"
        },
        {
          "city": "XENIA",
          "state": "OH",
          "status": "Fully Booked"
        },
        {
          "city": "YOUNGSTOWN",
          "state": "OH",
          "status": "Fully Booked"
        },
        {
          "city": "ZANESVILLE",
          "state": "OH",
          "status": "Fully Booked"
        }
      ]
    },
    "isBookingCompleted": true
  }
}
